blenderneuron/__init__.py
blenderneuron/activity.py
blenderneuron/commnode.py
blenderneuron/config.json
blenderneuron/neuronstart.py
blenderneuron/rootgroup.py
blenderneuron/section.py
blenderneuron/utils.py
blenderneuron/blender/__init__.py
blenderneuron/blender/blendernode.py
blenderneuron/blender/blenderroot.py
blenderneuron/blender/blenderrootgroup.py
blenderneuron/blender/utils.py
blenderneuron/blender/operators/__init__.py
blenderneuron/blender/operators/connection.py
blenderneuron/blender/operators/rootgroup.py
blenderneuron/blender/panels/__init__.py
blenderneuron/blender/panels/connection.py
blenderneuron/blender/panels/rootgroup.py
blenderneuron/blender/properties/__init__.py
blenderneuron/blender/properties/connection.py
blenderneuron/blender/properties/rootgroup.py
blenderneuron/blender/views/__init__.py
blenderneuron/blender/views/cellobjectview.py
blenderneuron/blender/views/curvecontainer.py
blenderneuron/blender/views/jsonview.py
blenderneuron/blender/views/objectview.py
blenderneuron/blender/views/sectionobjectview.py
blenderneuron/blender/views/synapseformerview.py
blenderneuron/blender/views/vectorconfinerview.py
blenderneuron/nrn/__init__.py
blenderneuron/nrn/neuronnode.py
blenderneuron/nrn/neuronrootgroup.py
blenderneuron/nrn/neuronsection.py
blenderneuron-2.1.1.dist-info/LICENSE.md
blenderneuron-2.1.1.dist-info/METADATA
blenderneuron-2.1.1.dist-info/WHEEL
blenderneuron-2.1.1.dist-info/top_level.txt
blenderneuron-2.1.1.dist-info/RECORD
