Metadata-Version: 2.1
Name: blenderneuron
Version: 2.1.1
Summary: Interface for Blender <-> NEURON
Author-email: Justas Birgiolas <justas@asu.edu>, Alistair Peet <no@email.com>
License: MIT
Project-URL: homepage, https://BlenderNEURON.org
Keywords: Blender,NEURON,neuroscience,visualization,neural networks,neurons,3D
Classifier: Intended Audience :: Science/Research
Classifier: License :: OSI Approved :: MIT License
Classifier: Natural Language :: English
Classifier: Operating System :: MacOS
Classifier: Operating System :: Microsoft :: Windows
Classifier: Operating System :: POSIX :: Linux
Classifier: Programming Language :: Python
Classifier: Topic :: Scientific/Engineering :: Visualization
Requires-Python: >=3.7
License-File: LICENSE.md
